arase/__init__.py
arase/client.py
arase/types.py
arase_sdk-1.3.0.dist-info/METADATA
arase_sdk-1.3.0.dist-info/WHEEL
arase_sdk-1.3.0.dist-info/licenses/LICENSE
arase_sdk-1.3.0.dist-info/RECORD
