Metadata-Version: 2.4
Name: arase-sdk
Version: 1.3.0
Summary: Official Python SDK for ARASE - AI-powered search engine API with stocks and weather
Project-URL: Homepage, https://arase.masarat.sa
Project-URL: Documentation, https://arase.masarat.sa/docs
Project-URL: Repository, https://github.com/masarat-sa/arase-python
Author-email: MASARAT SA <info@masarat.sa>
License-File: LICENSE
Keywords: ai,api,arase,saudi-arabia,search,web-search
Classifier: Development Status :: 5 - Production/Stable
Classifier: Intended Audience :: Developers
Classifier: License :: OSI Approved :: MIT License
Classifier: Operating System :: OS Independent
Classifier: Programming Language :: Python :: 3
Classifier: Programming Language :: Python :: 3.8
Classifier: Programming Language :: Python :: 3.9
Classifier: Programming Language :: Python :: 3.10
Classifier: Programming Language :: Python :: 3.11
Classifier: Programming Language :: Python :: 3.12
Classifier: Topic :: Internet :: WWW/HTTP :: Indexing/Search
Classifier: Typing :: Typed
Requires-Python: >=3.8
Requires-Dist: httpx>=0.24.0
